{
  "annotations": {
    "list": [
      {
        "builtIn": 1,
        "datasource": {
          "type": "grafana",
          "uid": "-- Grafana --"
        },
        "enable": true,
        "hide": true,
        "iconColor": "rgba(0, 211, 255, 1)",
        "name": "Annotations & Alerts",
        "type": "dashboard"
      }
    ]
  },
  "editable": true,
  "fiscalYearStartMonth": 0,
  "graphTooltip": 0,
  "id": 7,
  "links": [],
  "panels": [
    {
      "datasource": {
        "type": "influxdb",
        "uid": "df9ewp6gf53i8f"
      },
      "fieldConfig": {
        "defaults": {
          "color": {
            "fixedColor": "semi-dark-orange",
            "mode": "fixed"
          },
          "custom": {
            "axisBorderShow": false,
            "axisCenteredZero": false,
            "axisColorMode": "text",
            "axisLabel": "",
            "axisPlacement": "auto",
            "barAlignment": 0,
            "barWidthFactor": 0.6,
            "drawStyle": "line",
            "fillOpacity": 32,
            "gradientMode": "none",
            "hideFrom": {
              "legend": false,
              "tooltip": false,
              "viz": false
            },
            "insertNulls": false,
            "lineInterpolation": "smooth",
            "lineStyle": {
              "fill": "solid"
            },
            "lineWidth": 1,
            "pointSize": 5,
            "scaleDistribution": {
              "type": "linear"
            },
            "showPoints": "auto",
            "showValues": false,
            "spanNulls": false,
            "stacking": {
              "group": "A",
              "mode": "percent"
            },
            "thresholdsStyle": {
              "mode": "off"
            }
          },
          "displayName": "used",
          "mappings": [],
          "thresholds": {
            "mode": "absolute",
            "steps": [
              {
                "color": "green",
                "value": 0
              },
              {
                "color": "red",
                "value": 80
              }
            ]
          },
          "unit": "decmbytes"
        },
        "overrides": [
          {
            "matcher": {
              "id": "byName",
              "options": "memfree"
            },
            "properties": [
              {
                "id": "color",
                "value": {
                  "fixedColor": "super-light-green",
                  "mode": "fixed"
                }
              },
              {
                "id": "custom.showValues",
                "value": false
              },
              {
                "id": "displayName",
                "value": "free"
              }
            ]
          },
          {
            "matcher": {
              "id": "byName",
              "options": "cacheuse"
            },
            "properties": [
              {
                "id": "color",
                "value": {
                  "fixedColor": "blue",
                  "mode": "fixed"
                }
              },
              {
                "id": "displayName",
                "value": "cache"
              }
            ]
          }
        ]
      },
      "gridPos": {
        "h": 8,
        "w": 12,
        "x": 0,
        "y": 0
      },
      "id": 6,
      "options": {
        "legend": {
          "calcs": [
            "lastNotNull"
          ],
          "displayMode": "hidden",
          "placement": "bottom",
          "showLegend": false
        },
        "tooltip": {
          "hideZeros": false,
          "mode": "single",
          "sort": "none"
        }
      },
      "pluginVersion": "12.3.1",
      "targets": [
        {
          "dataset": "iox",
          "editorMode": "builder",
          "format": "table",
          "rawSql": "SELECT \"memuse\", \"memfree\", \"time\", \"cacheuse\" FROM \"sensors\" WHERE \"time\" >= $__timeFrom AND \"time\" <= $__timeTo AND \"station\" = 'humblepi' ",
          "refId": "A",
          "sql": {
            "columns": [
              {
                "parameters": [
                  {
                    "name": "memuse",
                    "type": "functionParameter"
                  }
                ],
                "type": "function"
              },
              {
                "parameters": [
                  {
                    "name": "memfree",
                    "type": "functionParameter"
                  }
                ],
                "type": "function"
              },
              {
                "parameters": [
                  {
                    "name": "time",
                    "type": "functionParameter"
                  }
                ],
                "type": "function"
              },
              {
                "parameters": [
                  {
                    "name": "cacheuse",
                    "type": "functionParameter"
                  }
                ],
                "type": "function"
              }
            ],
            "groupBy": [
              {
                "property": {
                  "type": "string"
                },
                "type": "groupBy"
              }
            ],
            "whereJsonTree": {
              "children1": [
                {
                  "id": "89ba88aa-cdef-4012-b456-719c0563f5c5",
                  "properties": {
                    "field": "station",
                    "fieldSrc": "field",
                    "operator": "equal",
                    "value": [
                      "humblepi"
                    ],
                    "valueError": [
                      null
                    ],
                    "valueSrc": [
                      "value"
                    ],
                    "valueType": [
                      "text"
                    ]
                  },
                  "type": "rule"
                }
              ],
              "id": "9a8a9bab-0123-4456-b89a-b19c055911bf",
              "type": "group"
            },
            "whereString": "station = 'humblepi'"
          },
          "table": "sensors"
        }
      ],
      "title": "memory",
      "type": "timeseries"
    },
    {
      "datasource": {
        "type": "influxdb",
        "uid": "df9ewp6gf53i8f"
      },
      "fieldConfig": {
        "defaults": {
          "color": {
            "mode": "palette-classic"
          },
          "custom": {
            "axisBorderShow": false,
            "axisCenteredZero": false,
            "axisColorMode": "text",
            "axisLabel": "",
            "axisPlacement": "auto",
            "barAlignment": 0,
            "barWidthFactor": 0.6,
            "drawStyle": "line",
            "fillOpacity": 0,
            "gradientMode": "none",
            "hideFrom": {
              "legend": false,
              "tooltip": false,
              "viz": false
            },
            "insertNulls": false,
            "lineInterpolation": "linear",
            "lineWidth": 1,
            "pointSize": 5,
            "scaleDistribution": {
              "type": "linear"
            },
            "showPoints": "auto",
            "showValues": false,
            "spanNulls": false,
            "stacking": {
              "group": "A",
              "mode": "none"
            },
            "thresholdsStyle": {
              "mode": "off"
            }
          },
          "mappings": [],
          "thresholds": {
            "mode": "absolute",
            "steps": [
              {
                "color": "green",
                "value": 0
              },
              {
                "color": "red",
                "value": 80
              }
            ]
          }
        },
        "overrides": []
      },
      "gridPos": {
        "h": 8,
        "w": 12,
        "x": 12,
        "y": 0
      },
      "id": 3,
      "options": {
        "legend": {
          "calcs": [],
          "displayMode": "list",
          "placement": "bottom",
          "showLegend": true
        },
        "tooltip": {
          "hideZeros": false,
          "mode": "single",
          "sort": "none"
        }
      },
      "pluginVersion": "12.3.1",
      "targets": [
        {
          "dataset": "iox",
          "editorMode": "builder",
          "format": "table",
          "rawSql": "SELECT \"throttled\", \"time\" FROM \"sensors\" WHERE \"time\" >= $__timeFrom AND \"time\" <= $__timeTo AND \"station\" = 'humblepi' ",
          "refId": "A",
          "sql": {
            "columns": [
              {
                "parameters": [
                  {
                    "name": "throttled",
                    "type": "functionParameter"
                  }
                ],
                "type": "function"
              },
              {
                "parameters": [
                  {
                    "name": "time",
                    "type": "functionParameter"
                  }
                ],
                "type": "function"
              }
            ],
            "groupBy": [
              {
                "property": {
                  "type": "string"
                },
                "type": "groupBy"
              }
            ],
            "whereJsonTree": {
              "children1": [
                {
                  "id": "ab9a8ba9-0123-4456-b89a-b19becc1d993",
                  "properties": {
                    "field": "station",
                    "fieldSrc": "field",
                    "operator": "equal",
                    "value": [
                      "humblepi"
                    ],
                    "valueError": [
                      null
                    ],
                    "valueSrc": [
                      "value"
                    ],
                    "valueType": [
                      "text"
                    ]
                  },
                  "type": "rule"
                }
              ],
              "id": "ba998baa-0123-4456-b89a-b19becb8a0d7",
              "type": "group"
            },
            "whereString": "station = 'humblepi'"
          },
          "table": "sensors"
        }
      ],
      "title": "cpu throttled",
      "type": "timeseries"
    },
    {
      "datasource": {
        "type": "influxdb",
        "uid": "df9ewp6gf53i8f"
      },
      "fieldConfig": {
        "defaults": {
          "color": {
            "mode": "thresholds"
          },
          "mappings": [],
          "thresholds": {
            "mode": "absolute",
            "steps": [
              {
                "color": "green",
                "value": 0
              },
              {
                "color": "red",
                "value": 80
              }
            ]
          }
        },
        "overrides": [
          {
            "matcher": {
              "id": "byName",
              "options": "time"
            },
            "properties": []
          },
          {
            "matcher": {
              "id": "byName",
              "options": "usr"
            },
            "properties": []
          },
          {
            "matcher": {
              "id": "byName",
              "options": "nice"
            },
            "properties": []
          },
          {
            "matcher": {
              "id": "byName",
              "options": "sys"
            },
            "properties": []
          },
          {
            "matcher": {
              "id": "byName",
              "options": "iowait"
            },
            "properties": []
          },
          {
            "matcher": {
              "id": "byName",
              "options": "irq"
            },
            "properties": []
          },
          {
            "matcher": {
              "id": "byName",
              "options": "soft"
            },
            "properties": []
          },
          {
            "matcher": {
              "id": "byName",
              "options": "steal"
            },
            "properties": []
          },
          {
            "matcher": {
              "id": "byName",
              "options": "gnice"
            },
            "properties": []
          },
          {
            "matcher": {
              "id": "byName",
              "options": "idle"
            },
            "properties": [
              {
                "id": "color",
                "value": {
                  "mode": "continuous-RdYlGr"
                }
              }
            ]
          }
        ]
      },
      "gridPos": {
        "h": 8,
        "w": 12,
        "x": 0,
        "y": 8
      },
      "id": 7,
      "options": {
        "minVizHeight": 75,
        "minVizWidth": 75,
        "orientation": "auto",
        "reduceOptions": {
          "calcs": [
            "lastNotNull"
          ],
          "fields": "",
          "values": false
        },
        "showThresholdLabels": false,
        "showThresholdMarkers": true,
        "sizing": "auto"
      },
      "pluginVersion": "12.3.1",
      "targets": [
        {
          "dataset": "iox",
          "editorMode": "builder",
          "format": "table",
          "rawSql": "SELECT \"time\", \"cpuusr\" AS \"usr\", \"cpunice\" AS \"nice\", \"cpusys\" AS \"sys\", \"cpuiowait\" AS \"iowait\", \"cpuirq\" AS \"irq\", \"cpusoft\" AS \"soft\", \"cpusteal\" AS \"steal\", \"cpugnice\" AS \"gnice\", \"cpuidle\" AS \"idle\" FROM \"sensors\" WHERE \"time\" >= $__timeFrom AND \"time\" <= $__timeTo AND (cpusys > 0 AND \"station\" = 'humblepi') ",
          "refId": "A",
          "sql": {
            "columns": [
              {
                "parameters": [
                  {
                    "name": "time",
                    "type": "functionParameter"
                  }
                ],
                "type": "function"
              },
              {
                "alias": "\"usr\"",
                "parameters": [
                  {
                    "name": "cpuusr",
                    "type": "functionParameter"
                  }
                ],
                "type": "function"
              },
              {
                "alias": "\"nice\"",
                "parameters": [
                  {
                    "name": "cpunice",
                    "type": "functionParameter"
                  }
                ],
                "type": "function"
              },
              {
                "alias": "\"sys\"",
                "parameters": [
                  {
                    "name": "cpusys",
                    "type": "functionParameter"
                  }
                ],
                "type": "function"
              },
              {
                "alias": "\"iowait\"",
                "parameters": [
                  {
                    "name": "cpuiowait",
                    "type": "functionParameter"
                  }
                ],
                "type": "function"
              },
              {
                "alias": "\"irq\"",
                "parameters": [
                  {
                    "name": "cpuirq",
                    "type": "functionParameter"
                  }
                ],
                "type": "function"
              },
              {
                "alias": "\"soft\"",
                "parameters": [
                  {
                    "name": "cpusoft",
                    "type": "functionParameter"
                  }
                ],
                "type": "function"
              },
              {
                "alias": "\"steal\"",
                "parameters": [
                  {
                    "name": "cpusteal",
                    "type": "functionParameter"
                  }
                ],
                "type": "function"
              },
              {
                "alias": "\"gnice\"",
                "parameters": [
                  {
                    "name": "cpugnice",
                    "type": "functionParameter"
                  }
                ],
                "type": "function"
              },
              {
                "alias": "\"idle\"",
                "parameters": [
                  {
                    "name": "cpuidle",
                    "type": "functionParameter"
                  }
                ],
                "type": "function"
              }
            ],
            "groupBy": [
              {
                "property": {
                  "type": "string"
                },
                "type": "groupBy"
              }
            ],
            "whereJsonTree": {
              "children1": [
                {
                  "id": "98b9a988-0123-4456-b89a-b19c0bbdc32d",
                  "properties": {
                    "field": "cpusys",
                    "fieldSrc": "field",
                    "operator": "greater",
                    "value": [
                      0
                    ],
                    "valueError": [
                      null
                    ],
                    "valueSrc": [
                      "value"
                    ],
                    "valueType": [
                      "number"
                    ]
                  },
                  "type": "rule"
                },
                {
                  "id": "ba999b98-0123-4456-b89a-b19c0cff4bae",
                  "properties": {
                    "field": "station",
                    "fieldSrc": "field",
                    "operator": "equal",
                    "value": [
                      "humblepi"
                    ],
                    "valueError": [
                      null
                    ],
                    "valueSrc": [
                      "value"
                    ],
                    "valueType": [
                      "text"
                    ]
                  },
                  "type": "rule"
                }
              ],
              "id": "b988aab9-0123-4456-b89a-b19c0b2eb6ed",
              "type": "group"
            },
            "whereString": "(cpusys > 0 AND station = 'humblepi')"
          },
          "table": "sensors"
        }
      ],
      "title": "cpu",
      "type": "gauge"
    },
    {
      "datasource": {
        "type": "influxdb",
        "uid": "df9ewp6gf53i8f"
      },
      "fieldConfig": {
        "defaults": {
          "color": {
            "mode": "palette-classic"
          },
          "custom": {
            "axisBorderShow": false,
            "axisCenteredZero": false,
            "axisColorMode": "text",
            "axisLabel": "",
            "axisPlacement": "auto",
            "barAlignment": 0,
            "barWidthFactor": 0.6,
            "drawStyle": "line",
            "fillOpacity": 0,
            "gradientMode": "none",
            "hideFrom": {
              "legend": false,
              "tooltip": false,
              "viz": false
            },
            "insertNulls": false,
            "lineInterpolation": "smooth",
            "lineWidth": 1,
            "pointSize": 5,
            "scaleDistribution": {
              "type": "linear"
            },
            "showPoints": "auto",
            "showValues": false,
            "spanNulls": false,
            "stacking": {
              "group": "A",
              "mode": "none"
            },
            "thresholdsStyle": {
              "mode": "off"
            }
          },
          "mappings": [],
          "thresholds": {
            "mode": "absolute",
            "steps": [
              {
                "color": "green",
                "value": 0
              },
              {
                "color": "red",
                "value": 80
              }
            ]
          }
        },
        "overrides": [
          {
            "matcher": {
              "id": "byName",
              "options": "timestamp"
            },
            "properties": [
              {
                "id": "unit",
                "value": "dateTimeAsIsoNoDateIfToday"
              }
            ]
          }
        ]
      },
      "gridPos": {
        "h": 8,
        "w": 12,
        "x": 12,
        "y": 8
      },
      "id": 1,
      "options": {
        "legend": {
          "calcs": [],
          "displayMode": "list",
          "placement": "bottom",
          "showLegend": true
        },
        "tooltip": {
          "hideZeros": false,
          "mode": "single",
          "sort": "none"
        }
      },
      "pluginVersion": "12.3.1",
      "targets": [
        {
          "dataset": "iox",
          "datasource": {
            "type": "influxdb",
            "uid": "df9ewp6gf53i8f"
          },
          "editorMode": "builder",
          "format": "table",
          "rawSql": "SELECT \"temperature\", \"time\" FROM \"sensors\" WHERE \"time\" >= $__timeFrom AND \"time\" <= $__timeTo AND \"station\" = 'humblepi' ",
          "refId": "A",
          "sql": {
            "columns": [
              {
                "parameters": [
                  {
                    "name": "temperature",
                    "type": "functionParameter"
                  }
                ],
                "type": "function"
              },
              {
                "parameters": [
                  {
                    "name": "time",
                    "type": "functionParameter"
                  }
                ],
                "type": "function"
              }
            ],
            "groupBy": [
              {
                "property": {
                  "type": "string"
                },
                "type": "groupBy"
              }
            ],
            "whereJsonTree": {
              "children1": [
                {
                  "id": "a89aaa99-cdef-4012-b456-719becb9c5eb",
                  "properties": {
                    "field": "station",
                    "fieldSrc": "field",
                    "operator": "equal",
                    "value": [
                      "humblepi"
                    ],
                    "valueError": [
                      null
                    ],
                    "valueSrc": [
                      "value"
                    ],
                    "valueType": [
                      "text"
                    ]
                  },
                  "type": "rule"
                }
              ],
              "id": "ba998baa-0123-4456-b89a-b19becb8a0d7",
              "type": "group"
            },
            "whereString": "station = 'humblepi'"
          },
          "table": "sensors"
        }
      ],
      "title": "cpu temperature",
      "type": "timeseries"
    },
    {
      "datasource": {
        "type": "influxdb",
        "uid": "df9ewp6gf53i8f"
      },
      "fieldConfig": {
        "defaults": {
          "color": {
            "mode": "palette-classic"
          },
          "custom": {
            "hideFrom": {
              "legend": false,
              "tooltip": false,
              "viz": false
            }
          },
          "displayName": "Free",
          "fieldMinMax": false,
          "mappings": [],
          "unit": "decgbytes"
        },
        "overrides": [
          {
            "matcher": {
              "id": "byName",
              "options": "diskavail"
            },
            "properties": [
              {
                "id": "color",
                "value": {
                  "fixedColor": "green",
                  "mode": "fixed"
                }
              },
              {
                "id": "displayName",
                "value": "free"
              }
            ]
          },
          {
            "matcher": {
              "id": "byName",
              "options": "diskused"
            },
            "properties": [
              {
                "id": "displayName",
                "value": "used"
              },
              {
                "id": "color",
                "value": {
                  "fixedColor": "red",
                  "mode": "fixed"
                }
              }
            ]
          }
        ]
      },
      "gridPos": {
        "h": 8,
        "w": 12,
        "x": 0,
        "y": 16
      },
      "id": 4,
      "options": {
        "legend": {
          "displayMode": "list",
          "placement": "bottom",
          "showLegend": true,
          "values": [
            "percent",
            "value"
          ]
        },
        "pieType": "pie",
        "reduceOptions": {
          "calcs": [
            "lastNotNull"
          ],
          "fields": "",
          "values": false
        },
        "sort": "desc",
        "tooltip": {
          "hideZeros": false,
          "mode": "single",
          "sort": "none"
        }
      },
      "pluginVersion": "12.3.1",
      "targets": [
        {
          "dataset": "iox",
          "editorMode": "builder",
          "format": "table",
          "rawSql": "SELECT \"diskavail\", \"diskused\" FROM \"sensors\" WHERE \"time\" >= $__timeFrom AND \"time\" <= $__timeTo AND \"station\" = 'humblepi' ",
          "refId": "A",
          "sql": {
            "columns": [
              {
                "parameters": [
                  {
                    "name": "diskavail",
                    "type": "functionParameter"
                  }
                ],
                "type": "function"
              },
              {
                "parameters": [
                  {
                    "name": "diskused",
                    "type": "functionParameter"
                  }
                ],
                "type": "function"
              }
            ],
            "groupBy": [
              {
                "property": {
                  "type": "string"
                },
                "type": "groupBy"
              }
            ],
            "whereJsonTree": {
              "children1": [
                {
                  "id": "889a9a98-cdef-4012-b456-719bfd80d2e2",
                  "properties": {
                    "field": "station",
                    "fieldSrc": "field",
                    "operator": "equal",
                    "value": [
                      "humblepi"
                    ],
                    "valueError": [
                      null
                    ],
                    "valueSrc": [
                      "value"
                    ],
                    "valueType": [
                      "text"
                    ]
                  },
                  "type": "rule"
                }
              ],
              "id": "989ba88b-0123-4456-b89a-b19bfd7f34d6",
              "type": "group"
            },
            "whereString": "station = 'humblepi'"
          },
          "table": "sensors"
        }
      ],
      "title": "disk usage",
      "type": "piechart"
    },
    {
      "datasource": {
        "type": "influxdb",
        "uid": "df9ewp6gf53i8f"
      },
      "fieldConfig": {
        "defaults": {
          "color": {
            "mode": "palette-classic"
          },
          "custom": {
            "axisBorderShow": false,
            "axisCenteredZero": false,
            "axisColorMode": "text",
            "axisLabel": "",
            "axisPlacement": "auto",
            "barAlignment": 0,
            "barWidthFactor": 0.6,
            "drawStyle": "line",
            "fillOpacity": 0,
            "gradientMode": "none",
            "hideFrom": {
              "legend": false,
              "tooltip": false,
              "viz": false
            },
            "insertNulls": false,
            "lineInterpolation": "smooth",
            "lineWidth": 1,
            "pointSize": 5,
            "scaleDistribution": {
              "type": "linear"
            },
            "showPoints": "auto",
            "showValues": false,
            "spanNulls": false,
            "stacking": {
              "group": "A",
              "mode": "none"
            },
            "thresholdsStyle": {
              "mode": "off"
            }
          },
          "mappings": [],
          "thresholds": {
            "mode": "absolute",
            "steps": [
              {
                "color": "green",
                "value": 0
              },
              {
                "color": "red",
                "value": 80
              }
            ]
          }
        },
        "overrides": []
      },
      "gridPos": {
        "h": 8,
        "w": 12,
        "x": 12,
        "y": 16
      },
      "id": 2,
      "options": {
        "legend": {
          "calcs": [],
          "displayMode": "list",
          "placement": "bottom",
          "showLegend": true
        },
        "tooltip": {
          "hideZeros": false,
          "mode": "single",
          "sort": "none"
        }
      },
      "pluginVersion": "12.3.1",
      "targets": [
        {
          "dataset": "iox",
          "editorMode": "builder",
          "format": "table",
          "rawSql": "SELECT \"voltage\", \"time\" FROM \"sensors\" WHERE \"time\" >= $__timeFrom AND \"time\" <= $__timeTo AND \"station\" = 'humblepi' ",
          "refId": "A",
          "sql": {
            "columns": [
              {
                "parameters": [
                  {
                    "name": "voltage",
                    "type": "functionParameter"
                  }
                ],
                "type": "function"
              },
              {
                "parameters": [
                  {
                    "name": "time",
                    "type": "functionParameter"
                  }
                ],
                "type": "function"
              }
            ],
            "groupBy": [
              {
                "property": {
                  "type": "string"
                },
                "type": "groupBy"
              }
            ],
            "whereJsonTree": {
              "children1": [
                {
                  "id": "88889ba9-0123-4456-b89a-b19becbfd69a",
                  "properties": {
                    "field": "station",
                    "fieldSrc": "field",
                    "operator": "equal",
                    "value": [
                      "humblepi"
                    ],
                    "valueError": [
                      null
                    ],
                    "valueSrc": [
                      "value"
                    ],
                    "valueType": [
                      "text"
                    ]
                  },
                  "type": "rule"
                }
              ],
              "id": "ba998baa-0123-4456-b89a-b19becb8a0d7",
              "type": "group"
            },
            "whereString": "station = 'humblepi'"
          },
          "table": "sensors"
        }
      ],
      "title": "cpu voltage",
      "type": "timeseries"
    }
  ],
  "preload": false,
  "schemaVersion": 42,
  "tags": [],
  "templating": {
    "list": []
  },
  "time": {
    "from": "now-6h",
    "to": "now"
  },
  "timepicker": {},
  "timezone": "browser",
  "title": "humblepi",
  "uid": "adn5zvr",
  "version": 39
}
